LICENSE
README.md
setup.cfg
setup.py
act/workers/__init__.py
act/workers/act_feed.py
act/workers/alienvault_otx.py
act/workers/argus_case.py
act/workers/attack.py
act/workers/country_regions.py
act/workers/crowdstrike_intel.py
act/workers/fact_chain_helper.py
act/workers/generic_uploader.py
act/workers/hybrid_analysis_feed.py
act/workers/ip_asn_history.py
act/workers/ip_filter.py
act/workers/isight.py
act/workers/mandiant_ti.py
act/workers/misp_feeds.py
act/workers/mnemonic_pdns.py
act/workers/scio.py
act/workers/search_graph.py
act/workers/shadowserver_asn.py
act/workers/shadowserver_enrich.py
act/workers/ta_helper.py
act/workers/template.py
act/workers/thaicert.py
act/workers/tool_alias.py
act/workers/update_ta_aliases_list.py
act/workers/url_shorter_unpack.py
act/workers/veris.py
act/workers/vt.py
act/workers/worker_config.py
act/workers/etc/act.ini
act/workers/etc/search_jobs.ini
act/workers/libs/__init__.py
act/workers/libs/argus.py
act/workers/libs/crowdstrike_intel.py
act/workers/libs/fact_chain.py
act/workers/libs/mandiant_ti_v4.py
act/workers/libs/misp.py
act/workers/libs/mnemonic.py
act/workers/libs/ta_list_methods.py
act/workers/libs/urlcache.py
act/workers/libs/worker.py
act_workers.egg-info/PKG-INFO
act_workers.egg-info/SOURCES.txt
act_workers.egg-info/dependency_links.txt
act_workers.egg-info/entry_points.txt
act_workers.egg-info/namespace_packages.txt
act_workers.egg-info/requires.txt
act_workers.egg-info/top_level.txt
act_workers.egg-info/zip-safe
test/test_argus_case.py
test/test_config.py
test/test_misp.py
test/test_scio.py
test/test_worker.py